{
  "pair": "XAGUSD",
  "direction": "BUY",
  "entry": 73.16,
  "sl": 71.4674128123692,
  "tp": 73.98053456987653,
  "rr": "1:0.5",
  "confidence": 83,
  "pattern": "Breakout Key Level",
  "atr": 0.3282138279506138,
  "cfd": {
    "reynolds": 0.42,
    "viscosity": 0.3185,
    "flowType": "LAMINAR/CONGESTION",
    "momentumAligned": true,
    "priceVelocity": 0.043158
  },
  "ew_context": "Elliott Wave analysis: bullish structure detected on M15",
  "pattern_desc": "Breakout Key Level pattern identified with 83% confidence.",
  "key_levels": "level: 71.7956 | touches: 4.0000",
  "invalidation": "Close beyond stop loss 71.4674",
  "market_context": "Technical setup on M15 timeframe.",
  "tags": [
    "breakout_key_level"
  ],
  "timeframe": "M15",
  "signal_type": "cfd",
  "saved_at": "2026-03-31T10:33:30.838Z",
  "outcome": "win"
}