{
  "pair": "AUD/JPY",
  "direction": "SELL",
  "entry": 111.68,
  "sl": 111.86,
  "tp": 111.52,
  "tp2": 111.32,
  "rr": "1:2.0",
  "timeframe": "H1",
  "confidence": 55,
  "pattern": "H4 bearish bias price rejecting VWAP resistance",
  "pattern_desc": "H4 bearish bias price rejecting VWAP resistance",
  "ew_context": "Price at VWAP resistance inside value area suggests congestion; H4 bearish bias supports downside but inside bar compression and positive order flow reduce conviction.",
  "market_context": "RSI H1: 59.48041995336509 | H4 Bias: BEARISH",
  "key_levels": "Entry: 111.68 | SL: 111.86 | TP1: 111.52 | TP2: 111.32",
  "invalidation": "Break above BB upper invalidates bearish structure",
  "tags": [
    "ai",
    "audjpy",
    "sell",
    "h1"
  ],
  "source": "AI",
  "outcome": "open",
  "saved_at": "2026-06-25T08:07:15Z",
  "timestamp": "2026-06-25T08:07:15Z"
}