{
  "pair": "DOTUSD",
  "direction": "BUY",
  "pattern": "Breakout Key Level",
  "entry": 1.3110432624816895,
  "sl": 1.2943089082837105,
  "tp": 1.3364856541156769,
  "tp2": null,
  "confidence": 83,
  "rr": "1:1.5",
  "ew_context": "Price breaking above key resistance level suggesting completion of corrective phase - potential start of impulse wave 3",
  "pattern_desc": "Clean breakout above heavily tested resistance at 1.3045 with 5 prior touches. RSI at healthy 59% supports continuation higher.",
  "key_levels": "Key resistance turned support: 1.3045 (5 touches). Next resistance: 1.3125, 1.3263",
  "invalidation": "Close back below 1.3045 key level on H1 timeframe",
  "market_context": "Polkadot benefiting from broader crypto strength as regulatory clarity improves and institutional adoption continues",
  "tags": [
    "breakout",
    "key_resistance",
    "crypto_strength"
  ],
  "cfd": {
    "reynolds": 0.02,
    "viscosity": 0.418,
    "flowType": "LAMINAR/CONGESTION",
    "momentumAligned": true,
    "priceVelocity": 0.004085
  },
  "atr": 0.01017695665359497,
  "timeframe": "H1",
  "signal_type": "options",
  "saved_at": "2026-04-08T13:24:23.974Z",
  "outcome": "win"
}